unii/__init__.py
unii/__main__.py
unii/_version.py
unii/py.typed
unii/sia_code.py
unii/task_helper.py
unii/unii.py
unii/unii_command.py
unii/unii_command_data.py
unii/unii_connection.py
unii/unii_message.py
unii-1.0.0.dist-info/METADATA
unii-1.0.0.dist-info/WHEEL
unii-1.0.0.dist-info/licenses/LICENSE
unii-1.0.0.dist-info/RECORD
