Metadata-Version: 2.3
Name: unii
Version: 1.0.0
Summary: Library to interface with Alphatronics UNii security systems.
Project-URL: Homepage, https://unii-security.com/
Project-URL: Repository, https://github.com/unii-security/py-unii
Project-URL: Issues, https://github.com/unii-security/py-unii/issues
Author-email: Rogier van Staveren <rogier@batoid.com>
License: Apache-2.0
License-File: LICENSE
Classifier: Development Status :: 4 - Beta
Classifier: Intended Audience :: Developers
Classifier: License :: OSI Approved :: Apache Software License
Classifier: Operating System :: MacOS :: MacOS X
Classifier: Operating System :: POSIX
Classifier: Programming Language :: Python :: 3.11
Classifier: Programming Language :: Python :: 3.12
Classifier: Topic :: Security
Classifier: Topic :: Software Development :: Libraries :: Python Modules
Requires-Python: >=3.11
Requires-Dist: pycryptodome>=3.6.6
Requires-Dist: semver>=3.0.2
